pkywebdriver/DB.py
pkywebdriver/__init__.py
pkywebdriver/baseChrome.py
pkywebdriver/baseFirefox.py
pkywebdriver/basicBrowser.py
pkywebdriver/myBrowser.py
pkywebdriver/myBrowser2.py
pkywebdriver/myFirefox.py
pkywebdriver/utils.py
pkywebdriver/LIB/__init__.py
pkywebdriver/LIB/logger.py
pkywebdriver/LIB/yaml_read.py
pkywebdriver-0.0.9.dist-info/METADATA
pkywebdriver-0.0.9.dist-info/WHEEL
pkywebdriver-0.0.9.dist-info/top_level.txt
pkywebdriver-0.0.9.dist-info/RECORD
