Metadata-Version: 2.4
Name: pkywebdriver
Version: 0.0.9
Summary: selenium을 이용한 데이타 수집하기 위한 기본 브라우저 설정 - chrome, firefox 용
Home-page: 
Author: Lian Park
Author-email: g1000white@gmail.com
Keywords: python tutorial,pypi
Classifier: Programming Language :: Python :: 3.6
Classifier: Programming Language :: Python :: 3.7
Classifier: Programming Language :: Python :: 3.8
Classifier: Programming Language :: Python :: 3.9
Requires-Python: >=3.6
Requires-Dist: selenium
Dynamic: author
Dynamic: author-email
Dynamic: classifier
Dynamic: keywords
Dynamic: requires-dist
Dynamic: requires-python
Dynamic: summary
